notebookManagerPackageN/__init__.py
notebookManagerPackageN/notebook_manager.py
notebookManagerPackageN-0.3.dist-info/METADATA
notebookManagerPackageN-0.3.dist-info/WHEEL
notebookManagerPackageN-0.3.dist-info/top_level.txt
notebookManagerPackageN-0.3.dist-info/RECORD
